ntparse/__init__.py
ntparse/cli.py
ntparse/core.py
ntparse/formatter.py
ntparse/utils.py
ntparse-0.2.0.dist-info/licenses/LICENSE
ntparse-0.2.0.dist-info/METADATA
ntparse-0.2.0.dist-info/WHEEL
ntparse-0.2.0.dist-info/entry_points.txt
ntparse-0.2.0.dist-info/top_level.txt
ntparse-0.2.0.dist-info/RECORD
