Metadata-Version: 2.4
Name: ntparse
Version: 0.2.0
Summary: A lightweight Python package for parsing syscalls from ntdll.dll
Author-email: micREsoft <contact@reverseengineeri.ng>
License: MIT
Project-URL: Homepage, https://github.com/micREsoft/ntparse
Project-URL: Repository, https://github.com/micREsoft/ntparse
Project-URL: Issues, https://github.com/micREsoft/ntparse/issues
Classifier: Development Status :: 3 - Alpha
Classifier: Intended Audience :: Developers
Classifier: License :: OSI Approved :: MIT License
Classifier: Operating System :: Microsoft :: Windows
Classifier: Programming Language :: Python :: 3
Classifier: Programming Language :: Python :: 3.7
Classifier: Programming Language :: Python :: 3.8
Classifier: Programming Language :: Python :: 3.9
Classifier: Programming Language :: Python :: 3.10
Classifier: Programming Language :: Python :: 3.11
Classifier: Programming Language :: Python :: 3.12
Classifier: Topic :: Software Development :: Libraries :: Python Modules
Classifier: Topic :: System :: Operating System
Requires-Python: >=3.7
License-File: LICENSE
Requires-Dist: pefile>=2023.2.7
Requires-Dist: capstone>=4.0.2
Provides-Extra: dev
Requires-Dist: pytest>=7.0.0; extra == "dev"
Requires-Dist: pytest-cov>=4.0.0; extra == "dev"
Requires-Dist: black>=23.0.0; extra == "dev"
Requires-Dist: flake8>=6.0.0; extra == "dev"
Dynamic: license-file
